{
  "path_rules": [
    {
      "match": "history/characters/",
      "envelope": "E_LOOKUP_CHARACTERS"
    },
    {
      "match": "history/provinces/",
      "envelope": "E_LOOKUP_PROVINCES"
    },
    {
      "match": "common/culture/name_lists/",
      "envelope": "E_LOOKUP_NAMES"
    },
    {
      "match": "common/religion/holy_sites/",
      "envelope": "E_LOOKUP_HOLY_SITES"
    },
    {
      "match": "common/dynasties/",
      "envelope": "E_LOOKUP_DYNASTIES"
    },
    {
      "match": "licenses/",
      "envelope": "E_SKIP",
      "comment": "License text files are not CK3 scripts"
    },
    {
      "match": "credits.txt",
      "envelope": "E_SKIP",
      "comment": "Credits file is not a CK3 script"
    },
    {
      "match": "credit.txt",
      "envelope": "E_SKIP",
      "comment": "Credits file is not a CK3 script"
    },
    {
      "match": "description.txt",
      "envelope": "E_SKIP",
      "comment": "Description file is not a CK3 script"
    },
    {
      "match": "compatibility.txt",
      "envelope": "E_SKIP",
      "comment": "Compatibility info file is not a CK3 script"
    },
    {
      "match": "modding_info.txt",
      "envelope": "E_SKIP",
      "comment": "Modding info file is not a CK3 script"
    },
    {
      "match": "STEAM_DESCRIPTION.txt",
      "envelope": "E_SKIP",
      "comment": "Steam description file is not a CK3 script"
    },
    {
      "match": "changelog",
      "envelope": "E_SKIP",
      "comment": "Changelog files are not CK3 scripts"
    },
    {
      "match": "CHANGES.txt",
      "envelope": "E_SKIP",
      "comment": "Changelog file is not a CK3 script"
    },
    {
      "match": "Notes.txt",
      "envelope": "E_SKIP",
      "comment": "Notes file is not a CK3 script"
    },
    {
      "match": "intr.txt",
      "envelope": "E_SKIP",
      "comment": "Intro file is not a CK3 script"
    },
    {
      "match": "SpecialThanksContributors.txt",
      "envelope": "E_SKIP",
      "comment": "Credits file is not a CK3 script"
    },
    {
      "match": "House_Traditions.txt",
      "envelope": "E_SKIP",
      "comment": "Documentation file is not a CK3 script"
    },
    {
      "match": "README",
      "envelope": "E_SKIP",
      "comment": "README files are not CK3 scripts"
    },
    {
      "match": "gui/",
      "envelope": "E_SKIP"
    },
    {
      "match": "gfx/",
      "envelope": "E_SKIP"
    },
    {
      "match": "map_data/",
      "envelope": "E_SKIP"
    },
    {
      "match": "fonts/",
      "envelope": "E_SKIP"
    },
    {
      "match": "music/",
      "envelope": "E_SKIP"
    },
    {
      "match": "sound/",
      "envelope": "E_SKIP"
    },
    {
      "match": "dlc_metadata/",
      "envelope": "E_SKIP"
    },
    {
      "match": "content_source/",
      "envelope": "E_SKIP"
    }
  ],
  "extension_to_type": {
    ".txt": "script",
    ".yml": "localization",
    ".gui": "skip",
    ".gfx": "skip",
    ".json": "skip",
    ".py": "skip",
    ".info": "skip",
    ".md": "skip"
  },
  "type_to_envelope": {
    "script": "E_SCRIPT",
    "localization": "E_LOC",
    "skip": "E_SKIP"
  },
  "envelope_steps": {
    "E_SCRIPT": [
      "parse",
      "extract_symbols",
      "extract_refs"
    ],
    "E_LOC": [
      "parse_loc",
      "extract_loc_entries"
    ],
    "E_LOOKUP_CHARACTERS": [
      "extract_characters"
    ],
    "E_LOOKUP_PROVINCES": [
      "extract_provinces"
    ],
    "E_LOOKUP_NAMES": [
      "extract_names"
    ],
    "E_LOOKUP_HOLY_SITES": [
      "extract_holy_sites"
    ],
    "E_LOOKUP_DYNASTIES": [
      "extract_dynasties"
    ],
    "E_SKIP": []
  },
  "skip_extensions": [
    ".dds",
    ".png",
    ".jpg",
    ".jpeg",
    ".gif",
    ".bmp",
    ".tga",
    ".wav",
    ".mp3",
    ".ogg",
    ".bank",
    ".wem",
    ".mesh",
    ".anim",
    ".skeleton",
    ".asset",
    ".settings",
    ".shader",
    ".mod",
    ".ttf",
    ".otf",
    ".fnt",
    ".bik",
    ".bk2",
    ".psd"
  ]
}